xpca/__init__.py
xpca-0.0.1.dist-info/LICENSE
xpca-0.0.1.dist-info/METADATA
xpca-0.0.1.dist-info/WHEEL
xpca-0.0.1.dist-info/top_level.txt
xpca-0.0.1.dist-info/RECORD
